<?xml version="1.0" encoding="utf-8"?>
<annotation>
<folder>images</folder>
<filename>88990ce0-2_frame_1915.png</filename>
<source>
<database>MyDatabase</database>
<annotation>COCO2017</annotation>
<image>flickr</image>
<flickrid>NULL</flickrid>
<annotator>1</annotator>
</source>
<owner>
<flickrid>NULL</flickrid>
<name>Label Studio</name>
</owner>
<size>
<width>848</width>
<height>480</height>
<depth>3</depth>
</size>
<segmented>0</segmented>
<object>
<name>Red Light</name>
<pose>Unspecified</pose>
<truncated>0</truncated>
<difficult>0</difficult>
<bndbox>
<xmin>330</xmin>
<ymin>169</ymin>
<xmax>339</xmax>
<ymax>182</ymax>
</bndbox>
</object>
<object>
<name>Red Light</name>
<pose>Unspecified</pose>
<truncated>0</truncated>
<difficult>0</difficult>
<bndbox>
<xmin>374</xmin>
<ymin>168</ymin>
<xmax>382</xmax>
<ymax>180</ymax>
</bndbox>
</object>
<object>
<name>Red Plate</name>
<pose>Unspecified</pose>
<truncated>0</truncated>
<difficult>0</difficult>
<bndbox>
<xmin>335</xmin>
<ymin>163</ymin>
<xmax>378</xmax>
<ymax>188</ymax>
</bndbox>
</object>
<object>
<name>Blue Light</name>
<pose>Unspecified</pose>
<truncated>0</truncated>
<difficult>0</difficult>
<bndbox>
<xmin>689</xmin>
<ymin>268</ymin>
<xmax>718</xmax>
<ymax>308</ymax>
</bndbox>
</object>
<object>
<name>Blue Light</name>
<pose>Unspecified</pose>
<truncated>0</truncated>
<difficult>0</difficult>
<bndbox>
<xmin>777</xmin>
<ymin>277</ymin>
<xmax>806</xmax>
<ymax>316</ymax>
</bndbox>
</object>
<object>
<name>Blue Plate</name>
<pose>Unspecified</pose>
<truncated>0</truncated>
<difficult>0</difficult>
<bndbox>
<xmin>707</xmin>
<ymin>253</ymin>
<xmax>795</xmax>
<ymax>328</ymax>
</bndbox>
</object>
</annotation>
