<?xml version="1.0" encoding="utf-8"?>
<annotation>
<folder>images</folder>
<filename>943c6cb9-3_frame_175.png</filename>
<source>
<database>MyDatabase</database>
<annotation>COCO2017</annotation>
<image>flickr</image>
<flickrid>NULL</flickrid>
<annotator>1</annotator>
</source>
<owner>
<flickrid>NULL</flickrid>
<name>Label Studio</name>
</owner>
<size>
<width>848</width>
<height>480</height>
<depth>3</depth>
</size>
<segmented>0</segmented>
<object>
<name>Red Light</name>
<pose>Unspecified</pose>
<truncated>0</truncated>
<difficult>0</difficult>
<bndbox>
<xmin>144</xmin>
<ymin>94</ymin>
<xmax>168</xmax>
<ymax>123</ymax>
</bndbox>
</object>
<object>
<name>Red Light</name>
<pose>Unspecified</pose>
<truncated>0</truncated>
<difficult>0</difficult>
<bndbox>
<xmin>258</xmin>
<ymin>85</ymin>
<xmax>279</xmax>
<ymax>115</ymax>
</bndbox>
</object>
<object>
<name>Red Plate</name>
<pose>Unspecified</pose>
<truncated>0</truncated>
<difficult>0</difficult>
<bndbox>
<xmin>148</xmin>
<ymin>74</ymin>
<xmax>267</xmax>
<ymax>137</ymax>
</bndbox>
</object>
<object>
<name>Blue Light</name>
<pose>Unspecified</pose>
<truncated>0</truncated>
<difficult>0</difficult>
<bndbox>
<xmin>503</xmin>
<ymin>70</ymin>
<xmax>510</xmax>
<ymax>87</ymax>
</bndbox>
</object>
<object>
<name>Blue Light</name>
<pose>Unspecified</pose>
<truncated>0</truncated>
<difficult>0</difficult>
<bndbox>
<xmin>538</xmin>
<ymin>70</ymin>
<xmax>548</xmax>
<ymax>90</ymax>
</bndbox>
</object>
<object>
<name>Blue Plate</name>
<pose>Unspecified</pose>
<truncated>0</truncated>
<difficult>0</difficult>
<bndbox>
<xmin>507</xmin>
<ymin>62</ymin>
<xmax>541</xmax>
<ymax>98</ymax>
</bndbox>
</object>
</annotation>
