<?xml version="1.0" encoding="utf-8"?>
<annotation>
<folder>images</folder>
<filename>703ac552-7_frame_514.png</filename>
<source>
<database>MyDatabase</database>
<annotation>COCO2017</annotation>
<image>flickr</image>
<flickrid>NULL</flickrid>
<annotator>1</annotator>
</source>
<owner>
<flickrid>NULL</flickrid>
<name>Label Studio</name>
</owner>
<size>
<width>848</width>
<height>480</height>
<depth>3</depth>
</size>
<segmented>0</segmented>
<object>
<name>Red Light</name>
<pose>Unspecified</pose>
<truncated>0</truncated>
<difficult>0</difficult>
<bndbox>
<xmin>490</xmin>
<ymin>138</ymin>
<xmax>496</xmax>
<ymax>149</ymax>
</bndbox>
</object>
<object>
<name>Red Light</name>
<pose>Unspecified</pose>
<truncated>0</truncated>
<difficult>0</difficult>
<bndbox>
<xmin>468</xmin>
<ymin>138</ymin>
<xmax>473</xmax>
<ymax>147</ymax>
</bndbox>
</object>
<object>
<name>Red Plate</name>
<pose>Unspecified</pose>
<truncated>0</truncated>
<difficult>0</difficult>
<bndbox>
<xmin>468</xmin>
<ymin>133</ymin>
<xmax>497</xmax>
<ymax>152</ymax>
</bndbox>
</object>
</annotation>
