<?xml version="1.0" encoding="utf-8"?>
<annotation>
<folder>images</folder>
<filename>a2785c9d-8_frame_516.png</filename>
<source>
<database>MyDatabase</database>
<annotation>COCO2017</annotation>
<image>flickr</image>
<flickrid>NULL</flickrid>
<annotator>1</annotator>
</source>
<owner>
<flickrid>NULL</flickrid>
<name>Label Studio</name>
</owner>
<size>
<width>848</width>
<height>480</height>
<depth>3</depth>
</size>
<segmented>0</segmented>
<object>
<name>Blue Light</name>
<pose>Unspecified</pose>
<truncated>0</truncated>
<difficult>0</difficult>
<bndbox>
<xmin>622</xmin>
<ymin>121</ymin>
<xmax>627</xmax>
<ymax>131</ymax>
</bndbox>
</object>
<object>
<name>Blue Light</name>
<pose>Unspecified</pose>
<truncated>0</truncated>
<difficult>0</difficult>
<bndbox>
<xmin>658</xmin>
<ymin>121</ymin>
<xmax>664</xmax>
<ymax>133</ymax>
</bndbox>
</object>
<object>
<name>Blue Plate</name>
<pose>Unspecified</pose>
<truncated>0</truncated>
<difficult>0</difficult>
<bndbox>
<xmin>622</xmin>
<ymin>117</ymin>
<xmax>664</xmax>
<ymax>135</ymax>
</bndbox>
</object>
</annotation>
