<?xml version="1.0" encoding="utf-8"?>
<annotation>
<folder>images</folder>
<filename>9f77deff-8_frame_1006.png</filename>
<source>
<database>MyDatabase</database>
<annotation>COCO2017</annotation>
<image>flickr</image>
<flickrid>NULL</flickrid>
<annotator>1</annotator>
</source>
<owner>
<flickrid>NULL</flickrid>
<name>Label Studio</name>
</owner>
<size>
<width>848</width>
<height>480</height>
<depth>3</depth>
</size>
<segmented>0</segmented>
<object>
<name>Blue Light</name>
<pose>Unspecified</pose>
<truncated>0</truncated>
<difficult>0</difficult>
<bndbox>
<xmin>441</xmin>
<ymin>171</ymin>
<xmax>445</xmax>
<ymax>187</ymax>
</bndbox>
</object>
<object>
<name>Blue Light</name>
<pose>Unspecified</pose>
<truncated>0</truncated>
<difficult>0</difficult>
<bndbox>
<xmin>492</xmin>
<ymin>170</ymin>
<xmax>497</xmax>
<ymax>185</ymax>
</bndbox>
</object>
<object>
<name>Blue Plate</name>
<pose>Unspecified</pose>
<truncated>0</truncated>
<difficult>0</difficult>
<bndbox>
<xmin>441</xmin>
<ymin>163</ymin>
<xmax>497</xmax>
<ymax>193</ymax>
</bndbox>
</object>
</annotation>
